<?xml version="1.0" encoding="UTF-8"?>
<list xmlns:xsi="http://www.w3.org/2001/XMLSchema-instance" xsi:noNamespaceSchemaLocation="../../xsd/skills.xsd">
	<skill id="53100" toLevel="1" name="Heroic Miracle">
		<!-- A skill given only to Olympiad Heroes. Max HP +850. With a certain chance after an attack, activates a buff that increases Atk. Spd., Casting Spd. and Speed and continuously recovers MP. -->
		<icon>icon.skill0912</icon>
		<operateType>P</operateType>
		<magicLevel>1</magicLevel>
		<effects>
			<effect name="TriggerSkillByAttack">
				<attackerType>Creature</attackerType>
				<minDamage>1</minDamage>
				<chance>70</chance>
				<targetType>SELF</targetType>
				<isCritical>true</isCritical>
				<allowWeapons>ALL</allowWeapons>
				<skillId>53101</skillId> <!-- Heroic Miracle -->
				<skillLevel>1</skillLevel>
			</effect>
			<effect name="TriggerSkillByAttack">
				<attackerType>Creature</attackerType>
				<minDamage>1</minDamage>
				<chance>70</chance>
				<targetType>SELF</targetType>
				<skillId>53101</skillId> <!-- Heroic Miracle -->
				<skillLevel>1</skillLevel>
				<isCritical>false</isCritical>
				<allowWeapons>ALL</allowWeapons>
			</effect>
			<effect name="TriggerSkillByMagicType">
				<magicTypes>0;1;2;3;4</magicTypes>
				<skillId>53101</skillId> <!-- Heroic Miracle -->
				<skillLevel>1</skillLevel>
				<chance>70</chance>
				<targetType>SELF</targetType>
			</effect>
			<effect name="MaxHp">
				<amount>850</amount>
				<mode>DIFF</mode>
			</effect>
		</effects>
	</skill>
	<skill id="53101" toLevel="1" name="Heroic Miracle">
		<!-- Atk. Spd. +100. Casting Spd. +100. Speed +20. Continuously recovers MP. -->
		<icon>icon.skill0912</icon>
		<operateType>A1</operateType>
		<magicLevel>-1</magicLevel>
		<isMagic>4</isMagic>
		<reuseDelay>100000</reuseDelay>
		<abnormalTime>10</abnormalTime>
		<abnormalLevel>1</abnormalLevel>
		<abnormalType>HERO_BUFF</abnormalType>
		<abnormalVisualEffect>HEROIC_MIRACLE_AVE</abnormalVisualEffect>
		<isTriggeredSkill>true</isTriggeredSkill>
		<blockedInOlympiad>true</blockedInOlympiad>
		<canBeDispelled>false</canBeDispelled>
		<targetType>SELF</targetType>
		<affectScope>SINGLE</affectScope>
		<effects>
			<effect name="PhysicalAttackSpeed">
				<amount>100</amount>
				<mode>DIFF</mode>
			</effect>
			<effect name="MagicalAttackSpeed">
				<amount>100</amount>
				<mode>DIFF</mode>
			</effect>
			<effect name="Speed">
				<amount>20</amount>
				<mode>DIFF</mode>
			</effect>
			<effect name="ManaHealOverTime">
				<power>80</power>
				<ticks>1</ticks>
			</effect>
		</effects>
	</skill>
</list>
